{
"type": "FeatureCollection",
"name": "geo_06_短期入所療養介護（介護医療院）",
"crs": { "type": "name", "properties": { "name": "urn:ogc:def:crs:OGC:1.3:CRS84" } },
"features": [
{ "type": "Feature", "properties": { "内容": "天童温泉篠田介護医療院【短期入所療養介護（介護医療院）】山形県天童市鎌田1丁目7-1天童温泉篠田病院", "url": "https://www.kaigokensaku.mhlw.go.jp/06/index.php?action_kouhyou_detail_004_kani=true&JigyosyoCd=06B1600014-00&ServiceCd=551&Type=search", "url2": "https://www.tendo-shinoda.jp" }, "geometry": { "type": "Point", "coordinates": [ 140.3848188, 38.360368 ] } }
]
}
